convey/__init__.py
convey/__main__.py
convey/action.py
convey/action_controller.py
convey/aggregate.py
convey/args_controller.py
convey/attachment.py
convey/checker.py
convey/config.py
convey/contacts.py
convey/controller.py
convey/convert.py
convey/decorators.py
convey/definition.py
convey/dialogue.py
convey/field.py
convey/flag.py
convey/graph.py
convey/identifier.py
convey/infodicts.py
convey/informer.py
convey/ipc.py
convey/mail_draft.py
convey/mail_sender.py
convey/parser.py
convey/processor.py
convey/types.py
convey/utils.py
convey/web.py
convey/whois.py
convey/wizzard.py
convey/wrapper.py
convey/wsgi.py
convey/defaults/contacts_abroad.csv
convey/defaults/contacts_cc.csv
convey/defaults/convey.yaml
convey/defaults/template.eml
convey/defaults/template_abroad.eml
convey/defaults/uwsgi.ini
convey-1.5.4.dist-info/licenses/LICENSE.txt
convey-1.5.4.dist-info/METADATA
convey-1.5.4.dist-info/WHEEL
convey-1.5.4.dist-info/entry_points.txt
convey-1.5.4.dist-info/top_level.txt
convey-1.5.4.dist-info/RECORD
