Metadata-Version: 2.4
Name: convey
Version: 1.5.4
Summary: CSV processing and mutual conversion of web related data types
Home-page: https://github.com/CZ-NIC/convey
Author: Edvard Rejthar
Author-email: edvard.rejthar@nic.cz
License: GNU GPLv3
License-File: LICENSE.txt
Requires-Dist: appdirs
Requires-Dist: attrs
Requires-Dist: beautifulsoup4
Requires-Dist: chardet
Requires-Dist: colorama
Requires-Dist: envelope>=1.5.3
Requires-Dist: ezodf
Requires-Dist: humanize
Requires-Dist: ipdb
Requires-Dist: jinja2
Requires-Dist: jsonpickle>1.4
Requires-Dist: lxml
Requires-Dist: netaddr
Requires-Dist: openpyxl
Requires-Dist: pint
Requires-Dist: prompt_toolkit
Requires-Dist: py3-validate-email>=1.0.0
Requires-Dist: pygments
Requires-Dist: python-dateutil
Requires-Dist: pythondialog
Requires-Dist: requests
Requires-Dist: tabulate
Requires-Dist: xlrd
Requires-Dist: tldextract
Requires-Dist: mininterface[ui]
Dynamic: author
Dynamic: author-email
Dynamic: description
Dynamic: description-content-type
Dynamic: home-page
Dynamic: license
Dynamic: license-file
Dynamic: requires-dist
Dynamic: summary
